afragmenter/__init__.py
afragmenter/afdb_client.py
afragmenter/afragmenter.py
afragmenter/cli.py
afragmenter/format_result.py
afragmenter/graph.py
afragmenter/intervals.py
afragmenter/pae_handler.py
afragmenter/plotting.py
afragmenter/result.py
afragmenter/sequence_reader.py
afragmenter/structure_displacement.py
afragmenter/structure_viewer.py
afragmenter-0.0.6.dist-info/LICENSE
afragmenter-0.0.6.dist-info/METADATA
afragmenter-0.0.6.dist-info/WHEEL
afragmenter-0.0.6.dist-info/entry_points.txt
afragmenter-0.0.6.dist-info/RECORD
