Metadata-Version: 2.3
Name: AFragmenter
Version: 0.0.6
Summary: 
License: MIT
Author: Stefaan Verwimp
Author-email: stefaan.verwimp@gmail.com
Requires-Python: >=3.9
Classifier: Programming Language :: Python :: 3
Classifier: License :: OSI Approved :: MIT License
Classifier: Operating System :: OS Independent
Classifier: Intended Audience :: Science/Research
Classifier: Topic :: Scientific/Engineering :: Bio-Informatics
Requires-Dist: biopython (>=1.76,<2.0)
Requires-Dist: matplotlib (>=3.9.2,<4.0)
Requires-Dist: numpy (>=1.0.0)
Requires-Dist: python-igraph (>=0.10.3,<1.0.0)
Requires-Dist: requests (>=2.32.3,<3.0)
Requires-Dist: rich (>=13.8.1,<14.0)
Requires-Dist: rich-click (>=1.8.3,<2.0)
